text_box_wrapper/__init__.py
text_box_wrapper/wrapper.py
text_box_wrapper-0.1.5.dist-info/LICENSE
text_box_wrapper-0.1.5.dist-info/METADATA
text_box_wrapper-0.1.5.dist-info/WHEEL
text_box_wrapper-0.1.5.dist-info/top_level.txt
text_box_wrapper-0.1.5.dist-info/RECORD
