Metadata-Version: 2.1
Name: text-box-wrapper
Version: 0.1.5
Summary: A simple package to wrap text with ASCII art
Home-page: https://github.com/Hootrix/text-box-wrapper
Author: Ho
Author-email: hhtjim@gmail.com
Classifier: Development Status :: 3 - Alpha
Classifier: Intended Audience :: Developers
Classifier: License :: OSI Approved :: MIT License
Classifier: Programming Language :: Python :: 3
Classifier: Programming Language :: Python :: 3.6
Classifier: Programming Language :: Python :: 3.7
Classifier: Programming Language :: Python :: 3.8
Classifier: Programming Language :: Python :: 3.9
License-File: LICENSE
Requires-Dist: wcwidth
